depcon/__init__.py
depcon/_version.py
depcon/cli.py
depcon/generators.py
depcon/models.py
depcon/parsers.py
depcon-0.5.1.dist-info/METADATA
depcon-0.5.1.dist-info/WHEEL
depcon-0.5.1.dist-info/entry_points.txt
depcon-0.5.1.dist-info/licenses/LICENSE
depcon-0.5.1.dist-info/RECORD
