Metadata-Version: 2.4
Name: depcon
Version: 0.5.1
Summary: Convert legacy requirements files to modern pyproject.toml format with full PEP 621 support
Project-URL: Homepage, https://github.com/lancereinsmith/depcon
Project-URL: Bug Tracker, https://github.com/lancereinsmith/depcon/issues
Project-URL: Documentation, https://lancereinsmith.github.io/depcon/
Project-URL: Repository, https://github.com/lancereinsmith/depcon
Author-email: Lance Reinsmith <info@k2rad.com>
License: MIT
License-File: LICENSE
Keywords: conversion,dependencies,dependency-management,hatchling,pep621,pyproject,requirements,uv
Classifier: Development Status :: 4 - Beta
Classifier: Intended Audience :: Developers
Classifier: License :: OSI Approved :: MIT License
Classifier: Programming Language :: Python :: 3
Classifier: Programming Language :: Python :: 3.11
Classifier: Programming Language :: Python :: 3.12
Classifier: Programming Language :: Python :: 3.13
Classifier: Topic :: Software Development :: Build Tools
Classifier: Topic :: Software Development :: Libraries :: Python Modules
Requires-Python: >=3.12
Requires-Dist: click>=8.3.1
Requires-Dist: packaging>=26.0
Requires-Dist: pydantic>=2.12.5
Requires-Dist: rich>=14.3.1
Requires-Dist: tomli-w>=1.2.0
Requires-Dist: tomli>=2.4.0
